{
    "partname": "optimization",
    "runtime": 534.4086807440035,
    "results": {
        "CONF3": {
            "xtb_opt": {
                "energy": -556.5580066,
                "grad_norm": 0.000479622164,
                "converged": true,
                "geom": [
                    {
                        "element": "C",
                        "xyz": [
                            -1.9029272773315478,
                            -0.9429534698634646,
                            0.2648790030217214
                        ]
                    },
                    {
                        "element": "C",
                        "xyz": [
                            -1.2228123973071083,
                            -0.028002372963425972,
                            -0.7395885266376129
                        ]
                    },
                    {
                        "element": "S",
                        "xyz": [
                            -0.0006562370339138726,
                            1.1351950201821948,
                            -0.00051671183839586
                        ]
                    },
                    {
                        "element": "C",
                        "xyz": [
                            1.222432540095177,
                            -0.026596898082479115,
                            0.7393142674419982
                        ]
                    },
                    {
                        "element": "C",
                        "xyz": [
                            1.9028238463727138,
                            -0.9438472162997588,
                            -0.2628402873534303
                        ]
                    },
                    {
                        "element": "H",
                        "xyz": [
                            -2.6517113563572936,
                            -1.558108506763838,
                            -0.24730783690989375
                        ]
                    },
                    {
                        "element": "H",
                        "xyz": [
                            -1.190254068196749,
                            -1.6217087352398516,
                            0.742851303198934
                        ]
                    },
                    {
                        "element": "H",
                        "xyz": [
                            -2.4076330068252974,
                            -0.36758641814205145,
                            1.0467422672079385
                        ]
                    },
                    {
                        "element": "H",
                        "xyz": [
                            -1.955156121137445,
                            0.6259847886504488,
                            -1.2247917745536148
                        ]
                    },
                    {
                        "element": "H",
                        "xyz": [
                            -0.7323927876444953,
                            -0.6047633078743526,
                            -1.530180457386009
                        ]
                    },
                    {
                        "element": "H",
                        "xyz": [
                            1.9548351928730474,
                            0.6280384551689818,
                            1.2235350975223678
                        ]
                    },
                    {
                        "element": "H",
                        "xyz": [
                            0.7321260863101641,
                            -0.6020070626533166,
                            1.5309185187359902
                        ]
                    },
                    {
                        "element": "H",
                        "xyz": [
                            2.407239223184475,
                            -0.36973029364208376,
                            -1.045759635775238
                        ]
                    },
                    {
                        "element": "H",
                        "xyz": [
                            2.651748192417547,
                            -1.5580766992104151,
                            0.25032181903615564
                        ]
                    },
                    {
                        "element": "H",
                        "xyz": [
                            1.1899875411523562,
                            -1.6233988752209914,
                            -0.7394534222517389
                        ]
                    }
                ],
                "cycles": 22,
                "ecyc": [
                    -556.5574084,
                    -556.5575068,
                    -556.5575357,
                    -556.5575725,
                    -556.5575923,
                    -556.5576146,
                    -556.5576216,
                    -556.5576344,
                    -556.5576416,
                    -556.5576532,
                    -556.5576619,
                    -556.557675,
                    -556.5576929,
                    -556.5577105,
                    -556.5577768,
                    -556.5573091,
                    -556.5578976,
                    -556.5579559,
                    -556.5579762,
                    -556.5579944,
                    -556.5580028,
                    -556.5580066
                ],
                "gncyc": [
                    0.020499220951,
                    0.00535,
                    0.0027156,
                    0.0014504,
                    0.0019778,
                    0.0013218,
                    0.0004505,
                    0.0007136,
                    0.0010445,
                    0.001038313193,
                    0.001038515942,
                    0.0004714,
                    0.0019277,
                    0.001459,
                    0.0008512,
                    0.002794,
                    0.0027693,
                    0.0051143,
                    0.020227,
                    0.020206260905,
                    0.020205665466,
                    0.0069052,
                    0.003095,
                    0.0012244,
                    0.00192,
                    0.0013679,
                    0.0004858,
                    0.000479622164
                ]
            },
            "xtb_rrho": {
                "energy": 0.099060763292,
                "rmsd": null,
                "gibbs": {
                    "298.15": 0.099060763292
                },
                "enthalpy": {
                    "298.15": null
                },
                "entropy": {
                    "298.15": null
                },
                "symmetry": "c1",
                "symnum": 1,
                "linear": false
            },
            "gtot": -556.458945836708,
            "bmw": 0.1494867036932016
        },
        "CONF1": {
            "xtb_opt": {
                "energy": -556.5579953,
                "grad_norm": 0.000462542957,
                "converged": true,
                "geom": [
                    {
                        "element": "C",
                        "xyz": [
                            -1.9155625557716103,
                            -0.932419706287858,
                            0.2667882779364162
                        ]
                    },
                    {
                        "element": "C",
                        "xyz": [
                            -1.2203863990201398,
                            -0.031204810885753914,
                            -0.7399523979462997
                        ]
                    },
                    {
                        "element": "S",
                        "xyz": [
                            -1.0561217623619813e-05,
                            1.1335864767624844,
                            -0.00259423468723135
                        ]
                    },
                    {
                        "element": "C",
                        "xyz": [
                            1.2203965154516545,
                            -0.02852901707967794,
                            0.7388919467524397
                        ]
                    },
                    {
                        "element": "C",
                        "xyz": [
                            1.9158848979308014,
                            -0.933116191486432,
                            -0.26461010893790443
                        ]
                    },
                    {
                        "element": "H",
                        "xyz": [
                            -2.6507712267076013,
                            -1.5613565282716282,
                            -0.24822587679633482
                        ]
                    },
                    {
                        "element": "H",
                        "xyz": [
                            -1.2087219953765644,
                            -1.5982810208736686,
                            0.7705313529699702
                        ]
                    },
                    {
                        "element": "H",
                        "xyz": [
                            -2.4384263928711096,
                            -0.345935098599254,
                            1.0281662621613576
                        ]
                    },
                    {
                        "element": "H",
                        "xyz": [
                            -1.9450444392177537,
                            0.6205751318891425,
                            -1.2394724167099214
                        ]
                    },
                    {
                        "element": "H",
                        "xyz": [
                            -0.7256465237245046,
                            -0.618491810886261,
                            -1.5201879242157565
                        ]
                    },
                    {
                        "element": "H",
                        "xyz": [
                            1.944904615354327,
                            0.6250227603441567,
                            1.2363089338065445
                        ]
                    },
                    {
                        "element": "H",
                        "xyz": [
                            0.7255962209185532,
                            -0.6131964649857404,
                            1.5210472510819746
                        ]
                    },
                    {
                        "element": "H",
                        "xyz": [
                            2.650771180453793,
                            -1.5605030362879264,
                            0.25275280502117875
                        ]
                    },
                    {
                        "element": "H",
                        "xyz": [
                            1.2091945995103586,
                            -1.6005067868167366,
                            -0.7665397070112191
                        ]
                    },
                    {
                        "element": "H",
                        "xyz": [
                            2.4391899266922294,
                            -0.3491866501471278,
                            -1.0276402875688335
                        ]
                    }
                ],
                "cycles": 25,
                "ecyc": [
                    -556.557359,
                    -556.5574592,
                    -556.5574892,
                    -556.5575285,
                    -556.5575448,
                    -556.5575798,
                    -556.5575918,
                    -556.5576087,
                    -556.5576146,
                    -556.5576247,
                    -556.5576381,
                    -556.5576519,
                    -556.5576676,
                    -556.5577078,
                    -556.5577162,
                    -556.5577841,
                    -556.5578423,
                    -556.5578684,
                    -556.5578878,
                    -556.5579054,
                    -556.5579394,
                    -556.5579584,
                    -556.5579801,
                    -556.5579907,
                    -556.5579953
                ],
                "gncyc": [
                    0.020470993157,
                    0.0053309,
                    0.0027354,
                    0.0014918,
                    0.0020417,
                    0.0015838,
                    0.0012903,
                    0.0010523,
                    0.0007951,
                    0.000798109932,
                    0.000798488708,
                    0.0008752,
                    0.0010552,
                    0.0011208,
                    0.0011147,
                    0.0010106,
                    0.003351,
                    0.0097384,
                    0.006281,
                    0.006291395672,
                    0.006291309334,
                    0.0026234,
                    0.0013642,
                    0.0022499,
                    0.0018468,
                    0.0032263,
                    0.0020439,
                    0.0007322,
                    0.0010551,
                    0.001068509418,
                    0.001068976353,
                    0.000459,
                    0.000462542957
                ]
            },
            "xtb_rrho": {
                "energy": 0.099065278308,
                "rmsd": null,
                "gibbs": {
                    "298.15": 0.099065278308
                },
                "enthalpy": {
                    "298.15": null
                },
                "entropy": {
                    "298.15": null
                },
                "symmetry": "c1",
                "symnum": 1,
                "linear": false
            },
            "gtot": -556.458930021692,
            "bmw": 0.1470036647234084
        },
        "CONF2": {
            "xtb_opt": {
                "energy": -556.558003,
                "grad_norm": 0.000841787573,
                "converged": true,
                "geom": [
                    {
                        "element": "C",
                        "xyz": [
                            -1.9118276808705872,
                            -0.9325973486618917,
                            0.2571271290851683
                        ]
                    },
                    {
                        "element": "C",
                        "xyz": [
                            -1.2203613031839333,
                            -0.02435016911337975,
                            -0.7450889412698506
                        ]
                    },
                    {
                        "element": "S",
                        "xyz": [
                            4.703960733911319e-05,
                            1.138629638383733,
                            -0.0012486296099538457
                        ]
                    },
                    {
                        "element": "C",
                        "xyz": [
                            1.2203135145387778,
                            -0.022831014341502698,
                            0.7451846747656269
                        ]
                    },
                    {
                        "element": "C",
                        "xyz": [
                            1.9117011847745395,
                            -0.9331070752438887,
                            -0.25524695058374175
                        ]
                    },
                    {
                        "element": "H",
                        "xyz": [
                            -1.2046121535768706,
                            -1.6073073634645652,
                            0.7487616085608891
                        ]
                    },
                    {
                        "element": "H",
                        "xyz": [
                            -2.4269412411560527,
                            -0.35197619178685235,
                            1.0283192918748565
                        ]
                    },
                    {
                        "element": "H",
                        "xyz": [
                            -2.6538711169495968,
                            -1.5524124791787233,
                            -0.2596139422168286
                        ]
                    },
                    {
                        "element": "H",
                        "xyz": [
                            -1.946371755558656,
                            0.6297804092640031,
                            -1.239542195301466
                        ]
                    },
                    {
                        "element": "H",
                        "xyz": [
                            -0.7245047688003157,
                            -0.6056422514122992,
                            -1.5289561917617511
                        ]
                    },
                    {
                        "element": "H",
                        "xyz": [
                            1.946353940554097,
                            0.632342953890234,
                            1.2382123209794178
                        ]
                    },
                    {
                        "element": "H",
                        "xyz": [
                            0.7244887127074029,
                            -0.6024854795392031,
                            1.5302872677479873
                        ]
                    },
                    {
                        "element": "H",
                        "xyz": [
                            2.4267249367728763,
                            -0.35413074034801684,
                            -1.0277368461230716
                        ]
                    },
                    {
                        "element": "H",
                        "xyz": [
                            2.65383601737148,
                            -1.5517368813846564,
                            0.26277481734179564
                        ]
                    },
                    {
                        "element": "H",
                        "xyz": [
                            1.2045266076896428,
                            -1.6089608244326687,
                            -0.745372031905003
                        ]
                    }
                ],
                "cycles": 27,
                "ecyc": [
                    -556.557329,
                    -556.5574277,
                    -556.5574569,
                    -556.5574967,
                    -556.5575149,
                    -556.5575594,
                    -556.5575753,
                    -556.5575972,
                    -556.5576053,
                    -556.5576181,
                    -556.5576316,
                    -556.5576438,
                    -556.557657,
                    -556.5576828,
                    -556.5575169,
                    -556.5577641,
                    -556.5578069,
                    -556.5578365,
                    -556.5578581,
                    -556.5578791,
                    -556.557916,
                    -556.5579385,
                    -556.5579708,
                    -556.5579847,
                    -556.5579934,
                    -556.5580006,
                    -556.558003
                ],
                "gncyc": [
                    0.020478768614,
                    0.0053494,
                    0.0027176,
                    0.0014575,
                    0.0020629,
                    0.0016868,
                    0.0014558,
                    0.0013246,
                    0.0008916,
                    0.000892771945,
                    0.000893645572,
                    0.0009147,
                    0.0012277,
                    0.001236,
                    0.0008744,
                    0.0008071,
                    0.0018686,
                    0.015131,
                    0.005371,
                    0.005399149891,
                    0.005399111071,
                    0.0025487,
                    0.0012998,
                    0.0026761,
                    0.0024881,
                    0.002896,
                    0.0020945,
                    0.0014326,
                    0.001556,
                    0.001552237906,
                    0.001552165812,
                    0.0006667,
                    0.0009524,
                    0.0008391,
                    0.000841787573
                ]
            },
            "xtb_rrho": {
                "energy": 0.099064942906,
                "rmsd": null,
                "gibbs": {
                    "298.15": 0.099064942906
                },
                "enthalpy": {
                    "298.15": null
                },
                "entropy": {
                    "298.15": null
                },
                "symmetry": "c1",
                "symnum": 1,
                "linear": false
            },
            "gtot": -556.458938057094,
            "bmw": 0.14826006652909157
        },
        "CONF6": {
            "xtb_opt": {
                "energy": -556.5572418,
                "grad_norm": 0.000199897239,
                "converged": true,
                "geom": [
                    {
                        "element": "C",
                        "xyz": [
                            -2.212635186776239,
                            -0.8512070314624526,
                            0.2263123126983535
                        ]
                    },
                    {
                        "element": "C",
                        "xyz": [
                            -1.5538760089482289,
                            0.516102366873387,
                            0.3145467186902344
                        ]
                    },
                    {
                        "element": "S",
                        "xyz": [
                            0.06700874605358038,
                            0.6332523499721788,
                            -0.5494393367476152
                        ]
                    },
                    {
                        "element": "C",
                        "xyz": [
                            1.0917935944867492,
                            -0.46423154660753907,
                            0.5188385399369821
                        ]
                    },
                    {
                        "element": "C",
                        "xyz": [
                            2.555837346847277,
                            -0.34774403327483394,
                            0.12361067253047982
                        ]
                    },
                    {
                        "element": "H",
                        "xyz": [
                            -3.1804753689917677,
                            -0.8286521572533796,
                            0.7406134887396427
                        ]
                    },
                    {
                        "element": "H",
                        "xyz": [
                            -2.3843665901632596,
                            -1.1401181568957628,
                            -0.8147455227415858
                        ]
                    },
                    {
                        "element": "H",
                        "xyz": [
                            -1.6020489326786214,
                            -1.6236721699665169,
                            0.7026514123236278
                        ]
                    },
                    {
                        "element": "H",
                        "xyz": [
                            -1.4041469033277993,
                            0.8155892997744106,
                            1.3578350834153043
                        ]
                    },
                    {
                        "element": "H",
                        "xyz": [
                            -2.1819138660135624,
                            1.2785888707245692,
                            -0.15801933937669635
                        ]
                    },
                    {
                        "element": "H",
                        "xyz": [
                            0.9429136647715698,
                            -0.15803076292176416,
                            1.560130308636691
                        ]
                    },
                    {
                        "element": "H",
                        "xyz": [
                            0.7482800996135757,
                            -1.4973998784192222,
                            0.41064447622739797
                        ]
                    },
                    {
                        "element": "H",
                        "xyz": [
                            3.1596508748588015,
                            -1.0133358899887126,
                            0.748829896936036
                        ]
                    },
                    {
                        "element": "H",
                        "xyz": [
                            2.711933954874652,
                            -0.6362316516687492,
                            -0.9208931522759201
                        ]
                    },
                    {
                        "element": "H",
                        "xyz": [
                            2.9254268476038545,
                            0.6735186886263184,
                            0.25742960471389553
                        ]
                    }
                ],
                "cycles": 7,
                "ecyc": [
                    -556.5570716,
                    -556.557174,
                    -556.5571998,
                    -556.5572246,
                    -556.5572353,
                    -556.5572408,
                    -556.5572418
                ],
                "gncyc": [
                    0.019705002344,
                    0.0050863,
                    0.0026523,
                    0.0012751,
                    0.0018244,
                    0.0009147,
                    0.0002415,
                    0.0002015,
                    0.000199897239
                ]
            },
            "xtb_rrho": {
                "energy": 0.097932133005,
                "rmsd": null,
                "gibbs": {
                    "298.15": 0.097932133005
                },
                "enthalpy": {
                    "298.15": null
                },
                "entropy": {
                    "298.15": null
                },
                "symmetry": "c1",
                "symnum": 1,
                "linear": false
            },
            "gtot": -556.4593096669951,
            "bmw": 0.21976215914379355
        },
        "CONF8": {
            "xtb_opt": {
                "energy": -556.5568296,
                "grad_norm": 0.000346151732,
                "converged": true,
                "geom": [
                    {
                        "element": "C",
                        "xyz": [
                            -2.7278631302160345,
                            0.0883851634753871,
                            0.02195321533156515
                        ]
                    },
                    {
                        "element": "C",
                        "xyz": [
                            -1.4018714610656788,
                            -0.6553430175587034,
                            0.0186142640803031
                        ]
                    },
                    {
                        "element": "S",
                        "xyz": [
                            -5.7060325476463515e-05,
                            0.5385908802114316,
                            -0.0035662435843856863
                        ]
                    },
                    {
                        "element": "C",
                        "xyz": [
                            1.4019868515699443,
                            -0.6552744805212433,
                            -0.008376976817566505
                        ]
                    },
                    {
                        "element": "C",
                        "xyz": [
                            2.727808203356945,
                            0.08854385242976524,
                            -0.026314159563170902
                        ]
                    },
                    {
                        "element": "H",
                        "xyz": [
                            -2.8390610667046676,
                            0.7121623604643725,
                            -0.8702315505817455
                        ]
                    },
                    {
                        "element": "H",
                        "xyz": [
                            -3.5520331124031896,
                            -0.6320426100620338,
                            0.03469200615147712
                        ]
                    },
                    {
                        "element": "H",
                        "xyz": [
                            -2.825762384156025,
                            0.7282304345689277,
                            0.9042656861479871
                        ]
                    },
                    {
                        "element": "H",
                        "xyz": [
                            -1.3209585192015314,
                            -1.298946211870837,
                            -0.8638529706502702
                        ]
                    },
                    {
                        "element": "H",
                        "xyz": [
                            -1.3072840523404514,
                            -1.2825138529297408,
                            0.9114681632510924
                        ]
                    },
                    {
                        "element": "H",
                        "xyz": [
                            1.3228172436473127,
                            -1.2844017001714598,
                            0.8846125660097541
                        ]
                    },
                    {
                        "element": "H",
                        "xyz": [
                            1.305902073318239,
                            -1.296949292344826,
                            -0.890715040071807
                        ]
                    },
                    {
                        "element": "H",
                        "xyz": [
                            3.5520960824124823,
                            -0.6318562722832805,
                            -0.02946327110672235
                        ]
                    },
                    {
                        "element": "H",
                        "xyz": [
                            2.8236332447466115,
                            0.7143479330104098,
                            -0.9188725787540691
                        ]
                    },
                    {
                        "element": "H",
                        "xyz": [
                            2.8408551691217565,
                            0.7263879532354611,
                            0.8556295417536277
                        ]
                    }
                ],
                "cycles": 4,
                "ecyc": [
                    -556.5567254,
                    -556.5568202,
                    -556.5568278,
                    -556.5568296
                ],
                "gncyc": [
                    0.018558122279,
                    0.0047219,
                    0.0024767,
                    0.0007119,
                    0.0003476,
                    0.000346151732
                ]
            },
            "xtb_rrho": {
                "energy": 0.098377420881,
                "rmsd": null,
                "gibbs": {
                    "298.15": 0.098377420881
                },
                "enthalpy": {
                    "298.15": null
                },
                "entropy": {
                    "298.15": null
                },
                "symmetry": "c1",
                "symnum": 1,
                "linear": false
            },
            "gtot": -556.458452179119,
            "bmw": 0.08862082572484782
        },
        "CONF4": {
            "xtb_opt": {
                "energy": -556.5564773,
                "grad_norm": 0.000577443979,
                "converged": true,
                "geom": [
                    {
                        "element": "C",
                        "xyz": [
                            -1.741519851802347,
                            -1.1528116820371526,
                            0.173289333386976
                        ]
                    },
                    {
                        "element": "C",
                        "xyz": [
                            -1.510443126027988,
                            0.21186867970971218,
                            -0.45407465189922264
                        ]
                    },
                    {
                        "element": "S",
                        "xyz": [
                            0.02530720485338776,
                            1.067875886878696,
                            0.09563880705045229
                        ]
                    },
                    {
                        "element": "C",
                        "xyz": [
                            1.3290019445042045,
                            -0.07595232391957162,
                            -0.539476830339895
                        ]
                    },
                    {
                        "element": "C",
                        "xyz": [
                            1.8848841824400333,
                            -1.0263772248070422,
                            0.5108983578555841
                        ]
                    },
                    {
                        "element": "H",
                        "xyz": [
                            -1.7612752656628687,
                            -1.0898390158731974,
                            1.2654822413045947
                        ]
                    },
                    {
                        "element": "H",
                        "xyz": [
                            -2.7032355435474877,
                            -1.5548168485607359,
                            -0.16637383817230095
                        ]
                    },
                    {
                        "element": "H",
                        "xyz": [
                            -0.9643453115076268,
                            -1.8647014581506287,
                            -0.11843088924612237
                        ]
                    },
                    {
                        "element": "H",
                        "xyz": [
                            -2.317866273308168,
                            0.9020302332999525,
                            -0.18672305144337933
                        ]
                    },
                    {
                        "element": "H",
                        "xyz": [
                            -1.4886136660615046,
                            0.14196976939213465,
                            -1.5468784006823082
                        ]
                    },
                    {
                        "element": "H",
                        "xyz": [
                            0.8987260414027446,
                            -0.6185224582174801,
                            -1.3880289264853771
                        ]
                    },
                    {
                        "element": "H",
                        "xyz": [
                            2.1276577515447688,
                            0.5601731697274424,
                            -0.9341502705046689
                        ]
                    },
                    {
                        "element": "H",
                        "xyz": [
                            2.332765351091505,
                            -0.47180815972894113,
                            1.341014433947372
                        ]
                    },
                    {
                        "element": "H",
                        "xyz": [
                            1.1067073872660558,
                            -1.6774238272274287,
                            0.9178134982194677
                        ]
                    },
                    {
                        "element": "H",
                        "xyz": [
                            2.6635361022498794,
                            -1.6577053620337,
                            0.06624771178737868
                        ]
                    }
                ],
                "cycles": 7,
                "ecyc": [
                    -556.5563159,
                    -556.5564088,
                    -556.5564303,
                    -556.5564588,
                    -556.5564662,
                    -556.5564732,
                    -556.5564773
                ],
                "gncyc": [
                    0.020017164597,
                    0.0055729,
                    0.0021753,
                    0.001132,
                    0.0022372,
                    0.0014493,
                    0.0013142,
                    0.0005775,
                    0.000577443979
                ]
            },
            "xtb_rrho": {
                "energy": 0.099103029618,
                "rmsd": null,
                "gibbs": {
                    "298.15": 0.099103029618
                },
                "enthalpy": {
                    "298.15": null
                },
                "entropy": {
                    "298.15": null
                },
                "symmetry": "c1",
                "symnum": 1,
                "linear": false
            },
            "gtot": -556.4573742703819,
            "bmw": 0.02829645910049786
        },
        "CONF7": {
            "xtb_opt": {
                "energy": -556.5572245,
                "grad_norm": 0.000857497552,
                "converged": true,
                "geom": [
                    {
                        "element": "C",
                        "xyz": [
                            -2.1803241989599504,
                            -0.8319724534291971,
                            0.025478345445367274
                        ]
                    },
                    {
                        "element": "C",
                        "xyz": [
                            -1.5619146875389267,
                            0.4565627531397984,
                            0.5442542920896672
                        ]
                    },
                    {
                        "element": "S",
                        "xyz": [
                            0.07586007628381553,
                            0.8614962032712348,
                            -0.19066592445046912
                        ]
                    },
                    {
                        "element": "C",
                        "xyz": [
                            1.0879336331371845,
                            -0.5258914350846963,
                            0.48004559860082985
                        ]
                    },
                    {
                        "element": "C",
                        "xyz": [
                            2.5635901581773792,
                            -0.2611676979193268,
                            0.22256224296527347
                        ]
                    },
                    {
                        "element": "H",
                        "xyz": [
                            -2.311531556976308,
                            -0.7975865469428659,
                            -1.0598237530258428
                        ]
                    },
                    {
                        "element": "H",
                        "xyz": [
                            -1.5631915070892968,
                            -1.7008803505093464,
                            0.270935103172185
                        ]
                    },
                    {
                        "element": "H",
                        "xyz": [
                            -3.163293942338959,
                            -0.9816257356968244,
                            0.4863051870212493
                        ]
                    },
                    {
                        "element": "H",
                        "xyz": [
                            -1.4481821531625232,
                            0.4282358643350034,
                            1.6336928895359475
                        ]
                    },
                    {
                        "element": "H",
                        "xyz": [
                            -2.19852495848075,
                            1.3142195503230254,
                            0.3031254946162268
                        ]
                    },
                    {
                        "element": "H",
                        "xyz": [
                            0.8861983962858605,
                            -0.6030314392210486,
                            1.5542970125857836
                        ]
                    },
                    {
                        "element": "H",
                        "xyz": [
                            0.7799908831422215,
                            -1.4613963893279462,
                            0.00324217269274702
                        ]
                    },
                    {
                        "element": "H",
                        "xyz": [
                            2.769679023931091,
                            -0.1535815396266462,
                            -0.8473244183489874
                        ]
                    },
                    {
                        "element": "H",
                        "xyz": [
                            2.901978871163858,
                            0.6465288382738694,
                            0.7310401591523052
                        ]
                    },
                    {
                        "element": "H",
                        "xyz": [
                            3.1576032048156346,
                            -1.1022400997013169,
                            0.594042770278778
                        ]
                    }
                ],
                "cycles": 21,
                "ecyc": [
                    -556.5555611,
                    -556.5556908,
                    -556.5557436,
                    -556.555842,
                    -556.5559459,
                    -556.5560905,
                    -556.5562835,
                    -556.5565174,
                    -556.5566459,
                    -556.5567782,
                    -556.5568786,
                    -556.556975,
                    -556.55704,
                    -556.5570894,
                    -556.5571227,
                    -556.5571726,
                    -556.5571957,
                    -556.5572072,
                    -556.5572132,
                    -556.5572204,
                    -556.5572245
                ],
                "gncyc": [
                    0.019988089956,
                    0.0052416,
                    0.0025198,
                    0.0022202,
                    0.0034661,
                    0.0051271,
                    0.0080818,
                    0.0063838,
                    0.0069429,
                    0.006946242195,
                    0.006944543275,
                    0.0027413,
                    0.0034062,
                    0.0055749,
                    0.0059354,
                    0.003464,
                    0.003462,
                    0.0042276,
                    0.0042196,
                    0.004222624872,
                    0.004222287402,
                    0.0017121,
                    0.0018078,
                    0.0009981,
                    0.0017278,
                    0.0008606,
                    0.000857497552
                ]
            },
            "xtb_rrho": {
                "energy": 0.097974441415,
                "rmsd": null,
                "gibbs": {
                    "298.15": 0.097974441415
                },
                "enthalpy": {
                    "298.15": null
                },
                "entropy": {
                    "298.15": null
                },
                "symmetry": "c1",
                "symnum": 1,
                "linear": false
            },
            "gtot": -556.459250058585,
            "bmw": 0.20631696597550192
        },
        "CONF5": {
            "xtb_opt": {
                "energy": -556.5556746,
                "grad_norm": 0.000615707383,
                "converged": true,
                "geom": [
                    {
                        "element": "C",
                        "xyz": [
                            -1.8603309761857518,
                            -1.1219373626028246,
                            -0.34364799455872913
                        ]
                    },
                    {
                        "element": "C",
                        "xyz": [
                            -1.4603890122966325,
                            0.12275421826190272,
                            0.43278146912995685
                        ]
                    },
                    {
                        "element": "S",
                        "xyz": [
                            0.00957326527215,
                            1.0249608644632693,
                            -0.2217759905865167
                        ]
                    },
                    {
                        "element": "C",
                        "xyz": [
                            1.4172715242474796,
                            0.13202470002863795,
                            0.5677605228487187
                        ]
                    },
                    {
                        "element": "C",
                        "xyz": [
                            1.879045890431255,
                            -1.1266499373597314,
                            -0.15011185585339493
                        ]
                    },
                    {
                        "element": "H",
                        "xyz": [
                            -2.7885582354549707,
                            -1.5319350156952967,
                            0.07276787492800038
                        ]
                    },
                    {
                        "element": "H",
                        "xyz": [
                            -2.036446024056511,
                            -0.88862034698713,
                            -1.3978203591672569
                        ]
                    },
                    {
                        "element": "H",
                        "xyz": [
                            -1.095501299249847,
                            -1.8999969229297275,
                            -0.2871754479219961
                        ]
                    },
                    {
                        "element": "H",
                        "xyz": [
                            -1.2643275682069088,
                            -0.10706624082686694,
                            1.4854997870393343
                        ]
                    },
                    {
                        "element": "H",
                        "xyz": [
                            -2.270742413185456,
                            0.859034134773355,
                            0.4073647250613138
                        ]
                    },
                    {
                        "element": "H",
                        "xyz": [
                            2.228134340509923,
                            0.8675479577548054,
                            0.5970746624203401
                        ]
                    },
                    {
                        "element": "H",
                        "xyz": [
                            1.1345442592322015,
                            -0.079930816137209,
                            1.604484182744244
                        ]
                    },
                    {
                        "element": "H",
                        "xyz": [
                            2.1368682025620256,
                            -0.9138592660111577,
                            -1.1916778208476198
                        ]
                    },
                    {
                        "element": "H",
                        "xyz": [
                            2.772300502270657,
                            -1.5247287581103037,
                            0.34630473257325156
                        ]
                    },
                    {
                        "element": "H",
                        "xyz": [
                            1.1139599960218032,
                            -1.906315886761186,
                            -0.13698157093859087
                        ]
                    }
                ],
                "cycles": 5,
                "ecyc": [
                    -556.5555672,
                    -556.5556485,
                    -556.5556615,
                    -556.5556697,
                    -556.5556746
                ],
                "gncyc": [
                    0.019693283682,
                    0.0055709,
                    0.0019432,
                    0.0008487,
                    0.000737,
                    0.0006146,
                    0.000615707383
                ]
            },
            "xtb_rrho": {
                "energy": 0.099090567276,
                "rmsd": null,
                "gibbs": {
                    "298.15": 0.099090567276
                },
                "enthalpy": {
                    "298.15": null
                },
                "entropy": {
                    "298.15": null
                },
                "symmetry": "c1",
                "symnum": 1,
                "linear": false
            },
            "gtot": -556.456584032724,
            "bmw": 0.012253155109657257
        }
    },
    "settings": {
        "optcycles": 8,
        "maxcyc": 200,
        "threshold": 1.5,
        "hlow": 0.01,
        "gradthr": 0.01,
        "func": "r2scan-3c",
        "basis": "def2-tzvp",
        "prog": "orca",
        "sm": "smd",
        "gfnv": "gfn2",
        "optlevel": "normal",
        "run": true,
        "macrocycles": true,
        "crestcheck": true,
        "template": false,
        "constrain": false,
        "xtb_opt": true
    },
    "nconf_in": 8,
    "nconf_out": 8
}